Prueba testbench normal/uP.v
//Brandon Garrido 
//Carnet: 19421
// Ing. Mecatrónica

//Flip-Flop tipo D de 1 bit
module FF_1BIT (input wire clk, reset, enable, input wire D, output reg Q);
	always @ (posedge clk or posedge reset or enable)begin
		if (reset) begin //si resete==1
			Q <= 1'b0; //Q es cero
		end
    else if (enable) begin // sino si enable==1 -> Q = D
      Q <= D;//unblocking assignament
    end
	end
endmodule


//Program counter con contador con enable de 12 bits
module Program_Counter (input wire clk, reset, enable, load, input wire [11:0]loadPC, output reg [11:0]PC);
  always @ (posedge clk, posedge reset) begin
    if (reset) begin
      PC <= 12'b0;//valor inicial del PC tras el reset
    end
    else if (load) begin//si se activa el enable del load
      PC <= loadPC;     //se carga el loadPC de la RAM
    end
    else if (enable) begin// sino si el enable del counter==1 el contador aumenta en 1
      PC <= PC + 1;
    end
  end
endmodule

//Program ROM con memory.list hex
module Program_ROM (input wire [11:0] PC, output wire [7:0] program_byte);
  reg [7:0] mem [0:4095];// creacion de arreglo de memoria
  initial begin
      $readmemh("memory.list", mem);//lectura del archivo de datos
  end
  assign program_byte = mem[PC];// resultado leido de la memoria
endmodule//program rom implementada junto con una lista de datos en el memory list


//Fetch con Flip-Flip tipo D de 8 bits
module Fetch (input wire clk, reset, enable, input wire [7:0] program_byte, output wire [3:0] instr, oprnd);
  FF_1BIT FF1(clk, reset, enable, program_byte[7], instr[3]);//4bits más significativos para el instr
  FF_1BIT FF2(clk, reset, enable, program_byte[6], instr[2]);
  FF_1BIT FF3(clk, reset, enable, program_byte[5], instr[1]);
  FF_1BIT FF4(clk, reset, enable, program_byte[4], instr[0]);
  FF_1BIT FF5(clk, reset, enable, program_byte[3], oprnd[3]);//4bits menos significativos para el oprn
  FF_1BIT FF6(clk, reset, enable, program_byte[2], oprnd[2]);
  FF_1BIT FF7(clk, reset, enable, program_byte[1], oprnd[1]);
  FF_1BIT FF8(clk, reset, enable, program_byte[0], oprnd[0]);
endmodule


//Banderas de Carry on y cero con FF tipo D de 2 bits
module Flags(input wire clk, reset, enable, input wire [1:0] D, output wire [1:0] C_Z);
    FF_1BIT FF1(clk, reset, enable, D[1], C_Z[1]);//bit más significativo el del carry
    FF_1BIT FF2(clk, reset, enable, D[0], C_Z[0]);
endmodule

//Flip Flop Tipo T de 1 bit para el phase
module Phase(input wire clk, reset, enable, output wire phase);
  FF_1BIT F1(clk, reset, enable, ~phase, phase);
endmodule

// Decode con sentencia casex dentro de un bloque always
module Decode(input wire [6:0] Address, output reg [12:0] Control_Signals);
  always @(Address) begin
    casex(Address)//casex con la implementación de los casos de las 21 instrucciones
      7'bxxxxxx0: Control_Signals = 13'b1000000001000 ;//caso 1
      7'b00001x1: Control_Signals = 13'b0100000001000 ;//caso 2
      7'b00000x1: Control_Signals = 13'b1000000001000 ;//caso 3
      7'b00011x1: Control_Signals = 13'b1000000001000 ;//caso 4
      7'b00010x1: Control_Signals = 13'b0100000001000 ;//caso 5
      7'b0010xx1: Control_Signals = 13'b0001001000010 ;//caso 6
      7'b0011xx1: Control_Signals = 13'b1001001100000 ;//caso 7
      7'b0100xx1: Control_Signals = 13'b0011010000010 ;//caso 8
      7'b0101xx1: Control_Signals = 13'b0011010000100 ;//Caso 9
      7'b0110xx1: Control_Signals = 13'b1011010100000 ;//caso 10
      7'b0111xx1: Control_Signals = 13'b1000000111000 ;//caso 11
      7'b1000x11: Control_Signals = 13'b0100000001000 ;//caso 12
      7'b1000x01: Control_Signals = 13'b1000000001000 ;//caso 13
      7'b1001x11: Control_Signals = 13'b1000000001000 ;//caso 14
      7'b1001x01: Control_Signals = 13'b0100000001000 ;//caso 15
      7'b1010xx1: Control_Signals = 13'b0011011000010 ;//caso 16
      7'b1011xx1: Control_Signals = 13'b1011011100000 ;//caso 17
      7'b1100xx1: Control_Signals = 13'b0100000001000 ;//caso 18
      7'b1101xx1: Control_Signals = 13'b0000000001001 ;//caso 19
      7'b1110xx1: Control_Signals = 13'b0011100000010 ;//caso 20
      7'b1111xx1: Control_Signals = 13'b1011100100000 ;//caso 21
      default:    Control_Signals = 13'b0 ; // caso por default
    endcase
  end
endmodule

//Bus driver implementado con buffer triestado de 4 bits
module Bus_Driver(input wire enable, input wire [3:0] oprnd, output wire [3:0] data_bus);
  assign data_bus = enable ? oprnd : 4'bz;//enable o alta impedancia
endmodule

//ALU implementada con sentencia case con las 5 operaciones
module ALU(input wire [3:0] A, B, input wire [2:0] S, output reg [3:0] Y, output reg [1:0] C_Z);
  reg [4:0] result;

  always @(*) begin// operaciones de la ALU
    case(S)
      3'b000:   result = A;//ST
      3'b001:   result = A - B;//COMPI
      3'b010:   result = B;//LIT
      3'b011:   result = A + B;//ADDI
      3'b100:   result = {1'b0, A ~& B};//NANDI
      default:  result = 5'b0;
    endcase

    assign Y = result[3:0];
    assign C_Z = { result[4] , ~(result[3] | result[2] | result[1] | result[0])};//asignacion de las banderas de cero y carry on

  end
endmodule

//Acumulador implementado con un FF tipo D de 4 bits
module Accumulator(input wire clk, reset, enable, input wire [3:0] D, output wire [3:0] Accu) ;
  FF_1BIT FF1(clk, reset, enable, D[3], Accu[3]);
  FF_1BIT FF2(clk, reset, enable, D[2], Accu[2]);
  FF_1BIT FF3(clk, reset, enable, D[1], Accu[1]);
  FF_1BIT FF4(clk, reset, enable, D[0], Accu[0]);
endmodule


//RAM Read, write and enable implementada con bloques always
module RAM (input wire enable, write, read, input wire [11:0]address_RAM, inout [3:0]data);//inout lectura-escritura
  reg [3:0] RAM [0:4095];
  reg [3:0] data_out;

  assign data = (enable & read & ~write) ? data_out:4'bz;// modo lectura o alta impedancia

  always @ ( address_RAM or data or enable or write ) begin//escritura en la RAM
    if (enable && write) begin
      RAM[address_RAM] = data;
    end
  end

  always @ ( address_RAM or enable or write or read) begin//lectura de la ram
    if (enable && ~write && read) begin
      data_out = RAM[address_RAM];
    end
  end
endmodule


//Salida del procesador implementada con un FF de 4 bits
module FF_out(input wire clk, reset, enable, input wire [3:0] D, output wire [3:0] FF_out) ;
  FF_1BIT FF1(clk, reset, enable, D[3], FF_out[3]);
  FF_1BIT FF2(clk, reset, enable, D[2], FF_out[2]);
  FF_1BIT FF3(clk, reset, enable, D[1], FF_out[1]);
  FF_1BIT FF4(clk, reset, enable, D[0], FF_out[0]);
endmodule// acumulador implementado con un fliflop de 4 bits

// union de todos los modulos del microprocesador
module uP(input wire clock, reset, input wire [3:0] pushbuttons,
  output wire phase, c_flag, z_flag, output wire [3:0] instr, oprnd, accu, data_bus, FF_out,
  output wire [7:0] program_byte, output wire [11:0] PC, address_RAM);//inputs y outputs del microprocesador

  wire [1:0] ALU_flags, C_Z;//declaración de wires
  wire [12:0] Control_Signals;
  wire [6:0] Adress;
  wire [3:0] ALU_out;
  wire [6:0] Address;

  assign c_flag = C_Z[1];//asignación de las banderas a la salida
  assign z_flag = C_Z[0];//bit mas significativo para el carry y el menos para el zero
  assign address_RAM = {oprnd, program_byte};//concatenación del address_RAM
  assign Address = {instr, c_flag, z_flag, phase};//concatenación del Adress

	//Instanciación de módulos y conexión respectiva de los distintos cables de entrada y salida de caca elemento
  Program_Counter M_Program_Counter(clock, reset, Control_Signals[12], Control_Signals[11], address_RAM, PC);
  Program_ROM    M_Program_ROM(PC, program_byte);
  Fetch          M_Fetch(clock, reset, ~phase, program_byte, instr, oprnd);
  Phase          M_Phase(clock, reset, 1'b1, phase);
  Flags          M_Flags(clock, reset, Control_Signals[9], ALU_flags, C_Z);
  Decode         M_Decode(Address, Control_Signals);
  Accumulator    M_Accumulator(clock, reset, Control_Signals[10], ALU_out , accu);
  Bus_Driver     M_Bus_Driver1(Control_Signals[1], oprnd, data_bus);
  Bus_Driver     M_Bus_Driver2(Control_Signals[3], ALU_out, data_bus);
  RAM            M_RAM(Control_Signals[5], Control_Signals[4], Control_Signals[5], address_RAM, data_bus);
  ALU            M_ALU(accu, data_bus, Control_Signals[8:6], ALU_out, ALU_flags);
  FF_out         M_FF_out(clock, reset, Control_Signals[0], data_bus, FF_out);
  Bus_Driver     M_In(Control_Signals[2], pushbuttons, data_bus);

endmodule

Prueba testbench normal/uP_tb.v
module testbench();
  //Variables de entrada
  reg clock, reset;
  reg [3:0]pushbuttons;

  //Variables de salida
  wire phase, c_flag, z_flag;
  wire [3:0]instr, oprnd, data_bus, FF_out, accu;
  wire [7:0]program_byte;
  wire [11:0]pc, address_ram;
  //Instanciaciones
  uP MicroProcessor(clock, reset, pushbuttons, phase, c_flag, z_flag, instr, oprnd, data_bus, FF_out, accu, program_byte, pc, address_ram);

  always//clock
    #5 clock <=~clock;

    initial begin
    #2
    $display(" \n MicroProcessor - Nibbler ");
    $display("clock reset pushbuttons |  phase  c_flag   z_flag   instr   oprnd   data_bus  FF_out   accu   program_byte       PC          address_RAM ");
    $display("------------------------|----------------------------------------------------------------------------------------------------------------");
    $monitor("%b       %b       %b    |   %b       %b        %b      %b    %b     %b      %b    %b     %b     %b    %b ", clock, reset, pushbuttons, phase, c_flag, z_flag, instr, oprnd, data_bus, FF_out, accu, program_byte, pc, address_ram);

      reset = 1; clock = 0; pushbuttons = 4'b0;
  #1  reset = 0; pushbuttons = 4'b1010;
    end

    initial
      #410 $finish;
    initial begin
        $dumpfile("uP_tb.vcd");
        $dumpvars(0, testbench);
      end
  endmodule

Prueba testbench normal/uP_tb.vcd
$date
	Sun Nov 22 10:25:30 2020
$end
$version
	Icarus Verilog
$end
$timescale
	1ps
$end
$scope module testbench $end
$var wire 4 ! FF_out [3:0] $end
$var wire 1 " z_flag $end
$var wire 8 # program_byte [7:0] $end
$var wire 1 $ phase $end
$var wire 12 % pc [11:0] $end
$var wire 4 & oprnd [3:0] $end
$var wire 4 ' instr [3:0] $end
$var wire 4 ( data_bus [3:0] $end
$var wire 1 ) c_flag $end
$var wire 12 * address_ram [11:0] $end
$var wire 4 + accu [3:0] $end
$var reg 1 , clock $end
$var reg 4 - pushbuttons [3:0] $end
$var reg 1 . reset $end
$scope module MicroProcessor $end
$var wire 1 , clock $end
$var wire 4 / data_bus [3:0] $end
$var wire 4 0 pushbuttons [3:0] $end
$var wire 1 . reset $end
$var wire 1 " z_flag $end
$var wire 8 1 program_byte [7:0] $end
$var wire 1 $ phase $end
$var wire 4 2 oprnd [3:0] $end
$var wire 4 3 instr [3:0] $end
$var wire 1 ) c_flag $end
$var wire 12 4 address_RAM [11:0] $end
$var wire 4 5 accu [3:0] $end
$var wire 12 6 PC [11:0] $end
$var wire 4 7 FF_out [3:0] $end
$var wire 13 8 Control_Signals [12:0] $end
$var wire 2 9 C_Z [1:0] $end
$var wire 7 : Address [6:0] $end
$var wire 4 ; ALU_out [3:0] $end
$var wire 2 < ALU_flags [1:0] $end
$scope module M_ALU $end
$var wire 4 = B [3:0] $end
$var wire 3 > S [2:0] $end
$var wire 4 ? A [3:0] $end
$var reg 2 @ C_Z [1:0] $end
$var reg 4 A Y [3:0] $end
$var reg 5 B result [4:0] $end
$upscope $end
$scope module M_Accumulator $end
$var wire 4 C D [3:0] $end
$var wire 1 , clk $end
$var wire 1 D enable $end
$var wire 1 . reset $end
$var wire 4 E Accu [3:0] $end
$scope module FF1 $end
$var wire 1 F D $end
$var wire 1 , clk $end
$var wire 1 D enable $end
$var wire 1 . reset $end
$var reg 1 G Q $end
$upscope $end
$scope module FF2 $end
$var wire 1 H D $end
$var wire 1 , clk $end
$var wire 1 D enable $end
$var wire 1 . reset $end
$var reg 1 I Q $end
$upscope $end
$scope module FF3 $end
$var wire 1 J D $end
$var wire 1 , clk $end
$var wire 1 D enable $end
$var wire 1 . reset $end
$var reg 1 K Q $end
$upscope $end
$scope module FF4 $end
$var wire 1 L D $end
$var wire 1 , clk $end
$var wire 1 D enable $end
$var wire 1 . reset $end
$var reg 1 M Q $end
$upscope $end
$upscope $end
$scope module M_Bus_Driver1 $end
$var wire 4 N data_bus [3:0] $end
$var wire 1 O enable $end
$var wire 4 P oprnd [3:0] $end
$upscope $end
$scope module M_Bus_Driver2 $end
$var wire 4 Q data_bus [3:0] $end
$var wire 1 R enable $end
$var wire 4 S oprnd [3:0] $end
$upscope $end
$scope module M_Decode $end
$var wire 7 T Address [6:0] $end
$var reg 13 U Control_Signals [12:0] $end
$upscope $end
$scope module M_FF_out $end
$var wire 4 V D [3:0] $end
$var wire 1 , clk $end
$var wire 1 W enable $end
$var wire 1 . reset $end
$var wire 4 X FF_out [3:0] $end
$scope module FF1 $end
$var wire 1 Y D $end
$var wire 1 , clk $end
$var wire 1 W enable $end
$var wire 1 . reset $end
$var reg 1 Z Q $end
$upscope $end
$scope module FF2 $end
$var wire 1 [ D $end
$var wire 1 , clk $end
$var wire 1 W enable $end
$var wire 1 . reset $end
$var reg 1 \ Q $end
$upscope $end
$scope module FF3 $end
$var wire 1 ] D $end
$var wire 1 , clk $end
$var wire 1 W enable $end
$var wire 1 . reset $end
$var reg 1 ^ Q $end
$upscope $end
$scope module FF4 $end
$var wire 1 _ D $end
$var wire 1 , clk $end
$var wire 1 W enable $end
$var wire 1 . reset $end
$var reg 1 ` Q $end
$upscope $end
$upscope $end
$scope module M_Fetch $end
$var wire 1 , clk $end
$var wire 1 a enable $end
$var wire 1 . reset $end
$var wire 8 b program_byte [7:0] $end
$var wire 4 c oprnd [3:0] $end
$var wire 4 d instr [3:0] $end
$scope module FF1 $end
$var wire 1 e D $end
$var wire 1 , clk $end
$var wire 1 a enable $end
$var wire 1 . reset $end
$var reg 1 f Q $end
$upscope $end
$scope module FF2 $end
$var wire 1 g D $end
$var wire 1 , clk $end
$var wire 1 a enable $end
$var wire 1 . reset $end
$var reg 1 h Q $end
$upscope $end
$scope module FF3 $end
$var wire 1 i D $end
$var wire 1 , clk $end
$var wire 1 a enable $end
$var wire 1 . reset $end
$var reg 1 j Q $end
$upscope $end
$scope module FF4 $end
$var wire 1 k D $end
$var wire 1 , clk $end
$var wire 1 a enable $end
$var wire 1 . reset $end
$var reg 1 l Q $end
$upscope $end
$scope module FF5 $end
$var wire 1 m D $end
$var wire 1 , clk $end
$var wire 1 a enable $end
$var wire 1 . reset $end
$var reg 1 n Q $end
$upscope $end
$scope module FF6 $end
$var wire 1 o D $end
$var wire 1 , clk $end
$var wire 1 a enable $end
$var wire 1 . reset $end
$var reg 1 p Q $end
$upscope $end
$scope module FF7 $end
$var wire 1 q D $end
$var wire 1 , clk $end
$var wire 1 a enable $end
$var wire 1 . reset $end
$var reg 1 r Q $end
$upscope $end
$scope module FF8 $end
$var wire 1 s D $end
$var wire 1 , clk $end
$var wire 1 a enable $end
$var wire 1 . reset $end
$var reg 1 t Q $end
$upscope $end
$upscope $end
$scope module M_Flags $end
$var wire 2 u D [1:0] $end
$var wire 1 , clk $end
$var wire 1 v enable $end
$var wire 1 . reset $end
$var wire 2 w C_Z [1:0] $end
$scope module FF1 $end
$var wire 1 x D $end
$var wire 1 , clk $end
$var wire 1 v enable $end
$var wire 1 . reset $end
$var reg 1 y Q $end
$upscope $end
$scope module FF2 $end
$var wire 1 z D $end
$var wire 1 , clk $end
$var wire 1 v enable $end
$var wire 1 . reset $end
$var reg 1 { Q $end
$upscope $end
$upscope $end
$scope module M_In $end
$var wire 4 | data_bus [3:0] $end
$var wire 1 } enable $end
$var wire 4 ~ oprnd [3:0] $end
$upscope $end
$scope module M_Phase $end
$var wire 1 , clk $end
$var wire 1 !" enable $end
$var wire 1 . reset $end
$var wire 1 $ phase $end
$scope module F1 $end
$var wire 1 "" D $end
$var wire 1 , clk $end
$var wire 1 !" enable $end
$var wire 1 . reset $end
$var reg 1 $ Q $end
$upscope $end
$upscope $end
$scope module M_Program_Counter $end
$var wire 1 , clk $end
$var wire 1 #" enable $end
$var wire 1 $" load $end
$var wire 12 %" loadPC [11:0] $end
$var wire 1 . reset $end
$var reg 12 &" PC [11:0] $end
$upscope $end
$scope module M_Program_ROM $end
$var wire 12 '" PC [11:0] $end
$var wire 8 (" program_byte [7:0] $end
$upscope $end
$scope module M_RAM $end
$var wire 12 )" address_RAM [11:0] $end
$var wire 4 *" data [3:0] $end
$var wire 1 +" enable $end
$var wire 1 ," read $end
$var wire 1 -" write $end
$var reg 4 ." data_out [3:0] $end
$upscope $end
$upscope $end
$upscope $end
$enddefinitions $end
#0
$dumpvars
bx ."
x-"
x,"
x+"
bx *"
bx )"
bx ("
bx '"
bx &"
bx %"
x$"
x#"
x""
1!"
bx ~
x}
bx |
x{
xz
xy
xx
bx w
xv
bx u
xt
xs
xr
xq
xp
xo
xn
xm
xl
xk
xj
xi
xh
xg
xf
xe
bx d
bx c
bx b
xa
x`
x_
x^
x]
x\
x[
xZ
xY
bx X
xW
bx V
bx U
bx T
bx S
xR
bx Q
bx P
xO
bx N
xM
xL
xK
xJ
xI
xH
xG
xF
bx E
xD
bx C
bx B
bx A
bx @
bx ?
bx >
bx =
bx <
bx ;
bx :
bx 9
bx 8
bx 7
bx 6
bx 5
bx 4
bx 3
bx 2
bx 1
bx 0
bx /
x.
bx -
x,
bx +
bx *
x)
bx (
bx '
bx &
bx %
x$
bx #
x"
bx !
$end
#2
0Y
0[
0]
0_
b0 !
b0 /
b0 =
b0 N
b0 Q
b0 V
b0 |
b0 *"
0x
1z
0F
0H
0J
0L
0}
0W
b0 >
0,"
0-"
0+"
1R
0O
0D
0v
0$"
1#"
b1 <
b1 @
b1 u
b0 ;
b0 A
b0 C
b0 S
b0 B
0)
0"
1""
b1000000001000 8
b1000000001000 U
1a
1s
1q
1o
1m
0k
0i
1g
0e
0G
0I
0K
b0 (
b0 5
b0 ?
b0 E
0M
0Z
0\
0^
b0 +
b0 7
b0 X
0`
0f
0h
0j
b0 '
b0 3
b0 d
0l
0n
0p
0r
b0 &
b0 2
b0 P
b0 c
0t
0y
b0 9
b0 w
0{
b0 :
b0 T
0$
b1001111 *
b1001111 4
b1001111 %"
b1001111 )"
b1001111 #
b1001111 1
b1001111 b
b1001111 ("
b0 %
b0 6
b0 &"
b0 '"
b0 -
b0 0
b0 ~
0,
1.
#3
b1010 -
b1010 0
b1010 ~
0.
#5
1"
b1 9
b1 w
1{
0z
1F
1H
1J
1L
1Y
1[
1]
1_
b0 <
b0 @
b0 u
b1111 ;
b1111 A
b1111 C
b1111 S
b1111 B
b1111 !
b1111 /
b1111 =
b1111 N
b1111 Q
b1111 V
b1111 |
b1111 *"
b10 >
0R
1O
1D
1v
0#"
0""
b11010000010 8
b11010000010 U
0a
1k
1e
b100 '
b100 3
b100 d
1h
1n
1p
1r
b1111 &
b1111 2
b1111 P
b1111 c
1t
b100011 :
b100011 T
1$
b111111011111 *
b111111011111 4
b111111011111 %"
b111111011111 )"
b11011111 #
b11011111 1
b11011111 b
b11011111 ("
b1 %
b1 6
b1 &"
b1 '"
1,
#10
0,
#15
1l
b1101 '
b1101 3
b1101 d
1f
b1111 !
b1111 /
b1111 =
b1111 N
b1111 Q
b1111 V
b1111 |
b1111 *"
b0 >
1R
0O
0D
0v
1#"
0"
1""
b1000000001000 8
b1000000001000 U
1a
1G
1I
1K
b1111 (
b1111 5
b1111 ?
b1111 E
1M
b0 9
b0 w
0{
b1101000 :
b1101000 T
0$
1,
#20
0,
#25
1`
1^
1\
b1111 +
b1111 7
b1111 X
1Z
1W
0#"
0""
b1001 8
b1001 U
0a
0q
0o
0m
0e
b1101001 :
b1101001 T
1$
b111101010001 *
b111101010001 4
b111101010001 %"
b111101010001 )"
b1010001 #
b1010001 1
b1010001 b
b1010001 ("
b10 %
b10 6
b10 &"
b10 '"
1,
#30
0,
#35
0r
0p
b101010001 *
b101010001 4
b101010001 %"
b101010001 )"
b1 &
b1 2
b1 P
b1 c
0n
b101 '
b101 3
b101 d
0f
0W
1#"
1""
b1000000001000 8
b1000000001000 U
1a
b101000 :
b101000 T
0$
1,
#40
0,
#45
0z
1F
0H
1J
0L
0[
0_
b0 <
b0 @
b0 u
b1010 ;
b1010 A
b1010 C
b1010 S
b1010 B
b1010 !
b1010 /
b1010 =
b1010 N
b1010 Q
b1010 V
b1010 |
b1010 *"
1}
b10 >
0R
1D
1v
0#"
0""
b11010000100 8
b11010000100 U
0a
0s
0k
b101001 :
b101001 T
1$
b101000000 *
b101000000 4
b101000000 %"
b101000000 )"
b1000000 #
b1000000 1
b1000000 b
b1000000 ("
b11 %
b11 6
b11 &"
b11 '"
1,
#50
0,
#55
b1000000 *
b1000000 4
b1000000 %"
b1000000 )"
b0 &
b0 2
b0 P
b0 c
0t
b100 '
b100 3
b100 d
0l
0}
b0 >
1R
0D
0v
1#"
1""
b1000000001000 8
b1000000001000 U
1a
0I
b1010 (
b1010 5
b1010 ?
b1010 E
0M
b100000 :
b100000 T
0$
1,
#60
0,
#65
1z
0F
0J
0Y
0]
b1 <
b1 @
b1 u
b0 ;
b0 A
b0 C
b0 S
b0 B
b0 !
b0 /
b0 =
b0 N
b0 Q
b0 V
b0 |
b0 *"
b10 >
0R
1O
1D
1v
0#"
0""
b11010000010 8
b11010000010 U
0a
1s
1q
1o
1m
b100001 :
b100001 T
1$
b1001111 *
b1001111 4
b1001111 %"
b1001111 )"
b1001111 #
b1001111 1
b1001111 b
b1001111 ("
b100 %
b100 6
b100 &"
b100 '"
1,
#70
0,
#75
1t
1r
1p
b111101001111 *
b111101001111 4
b111101001111 %"
b111101001111 )"
b1111 &
b1111 2
b1111 P
b1111 c
1n
b0 !
b0 /
b0 =
b0 N
b0 Q
b0 V
b0 |
b0 *"
b0 >
1R
0O
0D
0v
1#"
1"
1""
b1000000001000 8
b1000000001000 U
1a
0G
b0 (
b0 5
b0 ?
b0 E
0K
b1 9
b1 w
1{
b100010 :
b100010 T
0$
1,
#80
0,
#85
0z
1F
1H
1J
1L
1Y
1[
1]
1_
b0 <
b0 @
b0 u
b1111 ;
b1111 A
b1111 C
b1111 S
b1111 B
b1111 !
b1111 /
b1111 =
b1111 N
b1111 Q
b1111 V
b1111 |
b1111 *"
b10 >
0R
1O
1D
1v
0#"
0""
b11010000010 8
b11010000010 U
0a
0s
0o
1i
0g
1e
b100011 :
b100011 T
1$
b111110101010 *
b111110101010 4
b111110101010 %"
b111110101010 )"
b10101010 #
b10101010 1
b10101010 b
b10101010 ("
b101 %
b101 6
b101 &"
b101 '"
1,
#90
0,
#95
0t
b101010101010 *
b101010101010 4
b101010101010 %"
b101010101010 )"
b1010 &
b1010 2
b1010 P
b1010 c
0p
1j
0h
b1010 '
b1010 3
b1010 d
1f
b1111 !
b1111 /
b1111 =
b1111 N
b1111 Q
b1111 V
b1111 |
b1111 *"
b0 >
1R
0O
0D
0v
1#"
0"
1""
b1000000001000 8
b1000000001000 U
1a
1G
1I
1K
b1111 (
b1111 5
b1111 ?
b1111 E
1M
b0 9
b0 w
0{
b1010000 :
b1010000 T
0$
1,
#100
0,
#105
1x
0H
0J
0[
0_
b10 <
b10 @
b10 u
b1001 ;
b1001 A
b1001 C
b1001 S
b11001 B
b1010 !
b1010 /
b1010 =
b1010 N
b1010 Q
b1010 V
b1010 |
b1010 *"
b11 >
0R
1O
1D
1v
0#"
0""
b11011000010 8
b11011000010 U
0a
0q
0e
b1010001 :
b1010001 T
1$
b101000101000 *
b101000101000 4
b101000101000 %"
b101000101000 )"
b101000 #
b101000 1
b101000 b
b101000 ("
b110 %
b110 6
b110 &"
b110 '"
1,
#110
0,
#115
b100000101000 *
b100000101000 4
b100000101000 %"
b100000101000 )"
b1000 &
b1000 2
b1000 P
b1000 c
0r
b10 '
b10 3
b10 d
0f
0]
0x
1Y
1_
b0 <
b0 @
b0 u
b1001 !
b1001 /
b1001 =
b1001 N
b1001 Q
b1001 V
b1001 |
b1001 *"
1F
0J
b0 >
1R
0O
0D
0v
1#"
b1001 ;
b1001 A
b1001 C
b1001 S
b1001 B
1)
1""
b1000000001000 8
b1000000001000 U
1a
0I
b1001 (
b1001 5
b1001 ?
b1001 E
0K
b10 9
b10 w
1y
b10100 :
b10100 T
0$
1,
#120
0,
#125
0)
b0 9
b0 w
0y
0F
0_
b1 ;
b1 A
b1 C
b1 S
b1 B
b1000 !
b1000 /
b1000 =
b1000 N
b1000 Q
b1000 V
b1000 |
b1000 *"
b1 >
0R
1O
1v
0#"
0""
b1001000010 8
b1001000010 U
0a
1q
0i
1g
b10001 :
b10001 T
1$
b100001001010 *
b100001001010 4
b100001001010 %"
b100001001010 )"
b1001010 #
b1001010 1
b1001010 b
b1001010 ("
b111 %
b111 6
b111 &"
b111 '"
1,
#130
0,
#135
b101001001010 *
b101001001010 4
b101001001010 %"
b101001001010 )"
b1010 &
b1010 2
b1010 P
b1010 c
1r
0j
b100 '
b100 3
b100 d
1h
1F
1Y
1_
b1001 ;
b1001 A
b1001 C
b1001 S
b1001 B
b1001 !
b1001 /
b1001 =
b1001 N
b1001 Q
b1001 V
b1001 |
b1001 *"
b0 >
1R
0O
0v
1#"
1""
b1000000001000 8
b1000000001000 U
1a
b100000 :
b100000 T
0$
1,
#140
0,
#145
1J
0L
1]
0_
b1010 ;
b1010 A
b1010 C
b1010 S
b1010 B
b1010 !
b1010 /
b1010 =
b1010 N
b1010 Q
b1010 V
b1010 |
b1010 *"
b10 >
0R
1O
1D
1v
0#"
0""
b11010000010 8
b11010000010 U
0a
0q
1o
1i
0g
b100001 :
b100001 T
1$
b101000101100 *
b101000101100 4
b101000101100 %"
b101000101100 )"
b101100 #
b101100 1
b101100 b
b101100 ("
b1000 %
b1000 6
b1000 &"
b1000 '"
1,
#150
0,
#155
0r
b110000101100 *
b110000101100 4
b110000101100 %"
b110000101100 )"
b1100 &
b1100 2
b1100 P
b1100 c
1p
1j
b10 '
b10 3
b10 d
0h
b1010 !
b1010 /
b1010 =
b1010 N
b1010 Q
b1010 V
b1010 |
b1010 *"
b0 >
1R
0O
0D
0v
1#"
1""
b1000000001000 8
b1000000001000 U
1a
1K
b1010 (
b1010 5
b1010 ?
b1010 E
0M
b10000 :
b10000 T
0$
1,
#160
0,
#165
1x
1H
1[
0]
b10 <
b10 @
b10 u
b1110 ;
b1110 A
b1110 C
b1110 S
b11110 B
b1100 !
b1100 /
b1100 =
b1100 N
b1100 Q
b1100 V
b1100 |
b1100 *"
b1 >
0R
1O
1v
0#"
0""
b1001000010 8
b1001000010 U
0a
1s
0o
0m
1e
b10001 :
b10001 T
1$
b110010100001 *
b110010100001 4
b110010100001 %"
b110010100001 )"
b10100001 #
b10100001 1
b10100001 b
b10100001 ("
b1001 %
b1001 6
b1001 &"
b1001 '"
1,
#170
0,
#175
1t
0p
b110100001 *
b110100001 4
b110100001 %"
b110100001 )"
b1 &
b1 2
b1 P
b1 c
0n
b1010 '
b1010 3
b1010 d
1f
0[
0x
0H
1]
b0 <
b0 @
b0 u
b1010 ;
b1010 A
b1010 C
b1010 S
b1010 B
b1010 !
b1010 /
b1010 =
b1010 N
b1010 Q
b1010 V
b1010 |
b1010 *"
b0 >
1R
0O
0v
1#"
1)
1""
b1000000001000 8
b1000000001000 U
1a
b10 9
b10 w
1y
b1010100 :
b1010100 T
0$
1,
#180
0,
#185
0)
b0 9
b0 w
0y
1L
0Y
0]
1_
b1011 ;
b1011 A
b1011 C
b1011 S
b1011 B
b1 !
b1 /
b1 =
b1 N
b1 Q
b1 V
b1 |
b1 *"
b11 >
0R
1O
1D
1v
0#"
0""
b11011000010 8
b11011000010 U
0a
1q
1m
1g
b1010001 :
b1010001 T
1$
b111101011 *
b111101011 4
b111101011 %"
b111101011 )"
b11101011 #
b11101011 1
b11101011 b
b11101011 ("
b1010 %
b1010 6
b1010 &"
b1010 '"
1,
#190
0,
#195
1r
b101111101011 *
b101111101011 4
b101111101011 %"
b101111101011 )"
b1011 &
b1011 2
b1011 P
b1011 c
1n
b1110 '
b1110 3
b1110 d
1h
1]
1Y
0[
1_
b1011 !
b1011 /
b1011 =
b1011 N
b1011 Q
b1011 V
b1011 |
b1011 *"
0H
1J
1L
b0 >
1R
0O
0D
0v
1#"
b1011 ;
b1011 A
b1011 C
b1011 S
b1011 B
1""
b1000000001000 8
b1000000001000 U
1a
b1011 (
b1011 5
b1011 ?
b1011 E
1M
b1110000 :
b1110000 T
0$
1,
#200
0,
#205
0F
1H
0J
0L
b100 ;
b100 A
b100 C
b100 S
b100 B
b100 >
0R
1O
1D
1v
0#"
0""
b11100000010 8
b11100000010 U
0a
0s
0q
0m
1k
0i
b1110001 :
b1110001 T
1$
b101111010000 *
b101111010000 4
b101111010000 %"
b101111010000 )"
b11010000 #
b11010000 1
b11010000 b
b11010000 ("
b1011 %
b1011 6
b1011 &"
b1011 '"
1,
#210
0,
#215
0t
0r
b11010000 *
b11010000 4
b11010000 %"
b11010000 )"
b0 &
b0 2
b0 P
b0 c
0n
1l
b1101 '
b1101 3
b1101 d
0j
0Y
0]
0_
1[
b100 !
b100 /
b100 =
b100 N
b100 Q
b100 V
b100 |
b100 *"
0F
0J
0L
b0 >
1R
0O
0D
0v
1#"
b100 ;
b100 A
b100 C
b100 S
b100 B
1""
b1000000001000 8
b1000000001000 U
1a
0G
1I
0K
b100 (
b100 5
b100 ?
b100 E
0M
b1101000 :
b1101000 T
0$
1,
#220
0,
#225
0`
0^
b100 +
b100 7
b100 X
0Z
1W
0#"
0""
b1001 8
b1001 U
0a
0e
b1101001 :
b1101001 T
1$
b1010000 *
b1010000 4
b1010000 %"
b1010000 )"
b1010000 #
b1010000 1
b1010000 b
b1010000 ("
b1100 %
b1100 6
b1100 &"
b1100 '"
1,
#230
0,
#235
b101 '
b101 3
b101 d
0f
0W
1#"
1""
b1000000001000 8
b1000000001000 U
1a
b101000 :
b101000 T
0$
1,
#240
0,
